uart_rx.v
// Simple UART transmitter
// Sends 8-bit data serially: start bit (0), 8 data bits (LSB first), stop bit (1)
// Uses a baud_tick from an external generator for timing (16x oversampling)
// FSM states: idle, start, data, stop
// tx_done goes high when transmission is complete

module uart_rx (
    input rx,
    input clk, rst, baud_tick,
    output reg rx_done,
    output reg [7:0] data_out
);
// FSM states - one-hot encoding (just for fun, does not have any significance untiil the code is not being executed on an FPGA)
    parameter [3:0] idle = 4'b0001,
                    start = 4'b0010,
                    data = 4'b0100,
                    stop = 4'b1000;

    reg [3:0] ps, ns;
    reg [3:0] tick_counter;     // Counts 0-15 for 16x oversampling
    reg [3:0] bit_index;
    reg [7:0] rx_data;

    // Sequential logic - state updates and counter management only
    always @(posedge clk or posedge rst) begin
        if (rst) begin
            ps <= idle;
            tick_counter <= 0;
            bit_index <= 0;
        end else begin
            ps <= ns;
        end
    end
   // Combinational next state logic - determines state transitions
    always @(*) begin
        case (ps)
            idle: begin
                if (~rx) begin
                    ns = start;
                end else begin
                    ns = idle;
                end
            end
            start : begin
                if (baud_tick) begin
                    if (tick_counter == 7) begin
                        ns = data;
                    end else begin
                        ns = start;
                    end
                end
            end
            data : begin
                if (baud_tick) begin
                    if (bit_index > 7) begin
                        ns = stop;
                    end else begin
                        ns = data;                        
                    end
                end else begin
                    ns = data; 
                end
            end
            stop : begin
                if (baud_tick) begin
                    if (tick_counter ==7) begin
                            ns = idle;
                    end else begin
                            ns = stop;
                        end
                end else begin
                    ns = stop;
                end
            end
            default : ns = idle;
        endcase
    end
    // Output logic - determines module outputs based on current state
    always @(posedge clk ) begin
        if (rst) begin
            tick_counter <=0;
            bit_index <= 0 ;
            rx_done <= 0;
            rx_data <= 0;
            data_out <= 0;
        end else begin
            case (ps)
            idle: begin
                if (baud_tick) begin
                    rx_done <= 0;
                    tick_counter <=0;
                    bit_index <= 0 ;
                    rx_data <= 'bz;
                end
            end 
            start : begin
                rx_done <=0;
                if (baud_tick) begin
                    if (tick_counter ==7) begin
                        tick_counter <= 0;
                    end else begin
                        tick_counter <= tick_counter + 1;
                    end
                end
            end
            data : begin
                if (baud_tick) begin
                    if (bit_index < 8) begin
                        if (tick_counter == 7) begin
                            rx_data [bit_index] <= rx;
                            tick_counter <= tick_counter + 1;
                    end
                    if (tick_counter == 15) begin
                        bit_index <= bit_index + 1;
                        tick_counter <=0;
                    end else begin
                        tick_counter <= tick_counter + 1;
                    end
                    end else begin
                        tick_counter <= 0;
                        bit_index <= 0;
                    end
                end    
            end
            stop : begin
                rx_done <= 0 ;
                if (baud_tick) begin
                    if(tick_counter==7) begin
                        data_out <= rx_data;
                        rx_done <= 1;                        
                        tick_counter<=0;                        
                    end else begin
                        tick_counter <= tick_counter + 1;
                    end
                end
            end
            default: begin
                rx_done <= 0;
                bit_index <= 0;
                tick_counter<=0;
            end
        endcase
        end
    end
endmodule

uart_tx.v
// Simple UART transmitter
// Sends 8-bit data serially: start bit (0), 8 data bits (LSB first), stop bit (1)
// Uses a baud_tick from an external generator for timing (16x oversampling)
// FSM states: idle, start, data, stop
// tx_done goes high when transmission is complete

module uart_tx (
    input [7:0] data_in,
    input clk, rst, start_tx, baud_tick,
    output reg tx_done,
    output reg tx_line
);
// FSM states - one-hot encoding (just for fun, does not have any significance untiil the code is not being executed on an FPGA)
    parameter [3:0] idle = 4'b0001,
                    start = 4'b0010,
                    data = 4'b0100,
                    stop = 4'b1000;

    reg [3:0] ps, ns;
    reg [3:0] tick_counter;     // Counts 0-15 for 16x oversampling
    reg [2:0] bit_index;
    reg[7:0] tx_data;

    // Sequential logic - state updates and counter management only
    always @(posedge clk or posedge rst) begin
        if (rst) begin
            ps <= idle;
            tick_counter <= 0;
            bit_index <= 0;
        end else begin
            ps <= ns;
        end
    end
   // Combinational next state logic - determines state transitions
    always @(*) begin
        case (ps)
            idle: begin
                if (start_tx) begin
                    ns = start;
                end else begin
                    ns = idle;
                end
            end
            start : begin
                if (baud_tick) begin
                    ns = data;
                end else begin
                    ns =start;
                end
            end
            data : begin
                if (baud_tick) begin
                    if (bit_index==7) begin
                        ns = stop;
                    end else begin
                        ns = data;                        
                    end
                end
            end
            stop : begin
                if (baud_tick && tx_done) begin
                    ns = idle;
                end else begin
                    ns = stop; 
                end
            end
            default : ns = ps;
        endcase
    end
    // Output logic - determines module outputs based on current state
    always @(posedge clk ) begin
        case (ps)
            idle: begin
                tx_line <= 1;
                if (start_tx) begin
                    tx_done <= 0;
                    tx_data <= data_in; 
                end else begin
                    tx_done <= 0;
                    tx_data <= 'bz;
                end
            end
            start : begin
                tx_done <= 0;
                tx_line <= 0;
                bit_index <= 0;
            end
            data : begin
            if (baud_tick) begin
                if (tick_counter==0) begin
                    tx_line <= tx_data[bit_index];
                    tick_counter <= tick_counter + 1; 
                end else begin
                    if (tick_counter == 15) begin
                        bit_index <= bit_index + 1;
                        tick_counter <=0;
                    end else begin
                        tick_counter <= tick_counter + 1;
                    end
                end
            end    
            end
            stop : begin
                if (baud_tick) begin
                    tx_line <= 1;
                    if (tick_counter == 15) begin
                        tx_done <= 1;                        
                        tick_counter <= 0;
                    end else begin
                        tick_counter <= tick_counter + 1;
                    end
                end
            end
            default: begin
                tx_done <= 1;
                tx_line <= 1;
                bit_index <= 0;
                tick_counter<=0;
            end
        endcase
    end
endmodule

baudgen.v
    module baudgen #(
        parameter baud_rate = 9600,  // baud rate of 9600
        parameter clock_freq = 50000000 // freq. of 50Mhz
    ) (
        input clk, rst,
        output reg baud_tick
    );
        // Oversampling factor — UART typically uses 16x oversampling
        localparam ticks = clock_freq / (baud_rate * 16) ;
        // Counter width is dynamically calculated to hold values up to 'ticks'
        // Using $clog2 ensures the counter always has enough bits.
        reg [$clog2(ticks)-1 :0 ] baud_counter; 
        
        always @(posedge clk or posedge rst) begin
            if (rst) begin
                baud_counter <= 0;
                baud_tick <= 0; 
            end else begin
                if (baud_counter == ticks - 1) begin // here ticks is taking care of over sampling rate already
                    baud_counter <=0;
                    baud_tick <= 1;
                end else begin
                    baud_counter <= baud_counter + 1;
                    baud_tick <= 0; 
                end 
            end
        end
    endmodule

uart.v
module uart #(
    parameter BAUD_RATE = 9600,
    parameter CLOCK_FREQ = 50000000
)(
    input clk,
    input rst,

    // Serial I/O
    input rx,
    output tx,

    // Transmit interface
    input [7:0] tx_data_in,
    input start_tx,
    output tx_done,

    // Receive interface
    output [7:0] rx_data_out,
    output rx_done
);

    wire baud_tick;

    // Baud generator instantiation
    baudgen #(
        .baud_rate(BAUD_RATE),
        .clock_freq(CLOCK_FREQ)
    ) baud_generator (
        .clk(clk),
        .rst(rst),
        .baud_tick(baud_tick)
    );

    // UART Transmitter instantiation
    uart_tx transmitter (
        .clk(clk),
        .rst(rst),
        .start_tx(start_tx),
        .baud_tick(baud_tick),
        .data_in(tx_data_in),
        .tx_done(tx_done),
        .tx_line(tx)
    );

    // UART Receiver instantiation
    uart_rx receiver (
        .clk(clk),
        .rst(rst),
        .baud_tick(baud_tick),
        .rx(rx),
        .rx_done(rx_done),
        .data_out(rx_data_out)
    );

endmodule

uart_tb.v
`timescale 1ns / 1ps
`include "uart.v"
`include "uart_tx.v"
`include "uart_rx.v"
`include "baudgen.v"

module uart_tb;

    // Parameters
    parameter BAUD_RATE = 9600;
    parameter CLOCK_FREQ = 50000000;

    // Clock period for 50 MHz
    localparam CLK_PERIOD = 20; // ns

    // Testbench Signals
    reg clk = 0;
    reg rst = 1;

    reg [7:0] tx_data_in = 8'h00;
    reg start_tx = 0;
    wire tx_done;

    wire [7:0] rx_data_out;
    wire rx_done;

    wire tx;
    wire rx;

    // UART top module instantiation
    uart #(
        .BAUD_RATE(BAUD_RATE),
        .CLOCK_FREQ(CLOCK_FREQ)
    ) dut (
        .clk(clk),
        .rst(rst),
        .rx(rx),
        .tx(tx),
        .tx_data_in(tx_data_in),
        .start_tx(start_tx),
        .tx_done(tx_done),
        .rx_data_out(rx_data_out),
        .rx_done(rx_done)
    );

    // Clock generation
    always #(CLK_PERIOD/2) clk = ~clk;

    // Loopback tx -> rx
    assign rx = tx;

    // Test Procedure
    initial begin
        $dumpfile("uart_tb.vcd");
        $dumpvars(0, uart_tb);

        // Reset
        rst = 1;
        #(10 * CLK_PERIOD);
        rst = 0;

        // Send first byte
        @(posedge clk);
        tx_data_in = 8'hA5; // 10100101
        start_tx = 1;
        @(posedge clk);
        start_tx = 0;

        // Wait for TX to complete
        wait (tx_done == 1);
        $display("TX done at %t", $time);

        // Wait for RX to complete
        wait (rx_done == 1);
        $display("RX done at %t", $time);
        $display("Received Byte: %02X", rx_data_out);

        // Done
        #(10 * CLK_PERIOD);
        $finish;
    end

endmodule

uart_tb.vcd
$date
	Thu Aug 14 21:29:37 2025
$end
$version
	Icarus Verilog
$end
$timescale
	1ps
$end
$scope module uart_tb $end
$var wire 1 ! rx $end
$var wire 8 " rx_data_out [7:0] $end
$var wire 1 # rx_done $end
$var wire 1 $ tx $end
$var wire 1 % tx_done $end
$var reg 1 & clk $end
$var reg 1 ' rst $end
$var reg 1 ( start_tx $end
$var reg 8 ) tx_data_in [7:0] $end
$scope module dut $end
$var wire 1 * baud_tick $end
$var wire 1 + clk $end
$var wire 1 , rst $end
$var wire 1 ! rx $end
$var wire 8 - rx_data_out [7:0] $end
$var wire 1 # rx_done $end
$var wire 1 . start_tx $end
$var wire 1 $ tx $end
$var wire 8 / tx_data_in [7:0] $end
$var wire 1 % tx_done $end
$scope module baud_generator $end
$var wire 1 + clk $end
$var wire 1 , rst $end
$var reg 9 0 baud_counter [8:0] $end
$var reg 1 1 baud_tick $end
$upscope $end
$scope module transmitter $end
$var wire 1 * baud_tick $end
$var wire 1 + clk $end
$var wire 8 2 data_in [7:0] $end
$var wire 1 , rst $end
$var wire 1 . start_tx $end
$var reg 3 3 bit_index [2:0] $end
$var reg 4 4 ns [3:0] $end
$var reg 4 5 ps [3:0] $end
$var reg 4 6 tick_counter [3:0] $end
$var reg 8 7 tx_data [7:0] $end
$var reg 1 8 tx_done $end
$var reg 1 9 tx_line $end
$upscope $end
$scope module receiver $end
$var wire 1 * baud_tick $end
$var wire 1 + clk $end
$var wire 1 , rst $end
$var wire 1 ! rx $end
$var reg 4 : bit_index [3:0] $end
$var reg 8 ; data_out [7:0] $end
$var reg 4 < ns [3:0] $end
$var reg 4 = ps [3:0] $end
$var reg 8 > rx_data [7:0] $end
$var reg 1 ? rx_done $end
$var reg 4 @ tick_counter [3:0] $end
$upscope $end
$upscope $end
$upscope $end
$enddefinitions $end
#0
$dumpvars
b0 @
x?
bx >
b1 =
b1 <
bx ;
b0 :
x9
x8
bx 7
b0 6
b1 5
b1 4
b0 3
b0 2
01
b0 0
b0 /
0.
bx -
1,
0+
0*
b0 )
0(
1'
0&
x%
x$
x#
bx "
x!
$end
#10000
bz 7
08
0%
19
1$
1!
b0 ;
b0 "
b0 -
b0 >
0?
0#
1&
1+
#20000
0&
0+
#30000
1&
1+
#40000
0&
0+
#50000
1&
1+
#60000
0&
0+
#70000
1&
1+
#80000
0&
0+
#90000
1&
1+
#100000
0&
0+
#110000
1&
1+
#120000
0&
0+
#130000
1&
1+
#140000
0&
0+
#150000
1&
1+
#160000
0&
0+
#170000
1&
1+
#180000
0&
0+
#190000
1&
1+
#200000
0&
0+
0'
0,
#210000
b10100101 7
b1 0
b10 4
1(
1.
b10100101 )
b10100101 /
b10100101 2
1&
1+
#220000
0&
0+
#230000
b10 0
b10 5
b10 4
0(
0.
1&
1+
#240000
0&
0+
#250000
b10 <
09
0$
0!
b11 0
1&
1+
#260000
0&
0+
#270000
b100 0
b10 =
1&
1+
#280000
0&
0+
#290000
b101 0
1&
1+
#300000
0&
0+
#310000
b110 0
1&
1+
#320000
0&
0+
#330000
b111 0
1&
1+
#340000
0&
0+
#350000
b1000 0
1&
1+
#360000
0&
0+
#370000
b1001 0
1&
1+
#380000
0&
0+
#390000
b1010 0
1&
1+
#400000
0&
0+
#410000
b1011 0
1&
1+
#420000
0&
0+
#430000
b1100 0
1&
1+
#440000
0&
0+
#450000
b1101 0
1&
1+
#460000
0&
0+
#470000
b1110 0
1&
1+
#480000
0&
0+
#490000
b1111 0
1&
1+
#500000
0&
0+
#510000
b10000 0
1&
1+
#520000
0&
0+
#530000
b10001 0
1&
1+
#540000
0&
0+
#550000
b10010 0
1&
1+
#560000
0&
0+
#570000
b10011 0
1&
1+
#580000
0&
0+
#590000
b10100 0
1&
1+
#600000
0&
0+
#610000
b10101 0
1&
1+
#620000
0&
0+
#630000
b10110 0
1&
1+
#640000
0&
0+
#650000
b10111 0
1&
1+
#660000
0&
0+
#670000
b11000 0
1&
1+
#680000
0&
0+
#690000
b11001 0
1&
1+
#700000
0&
0+
#710000
b11010 0
1&
1+
#720000
0&
0+
#730000
b11011 0
1&
1+
#740000
0&
0+
#750000
b11100 0
1&
1+
#760000
0&
0+
#770000
b11101 0
1&
1+
#780000
0&
0+
#790000
b11110 0
1&
1+
#800000
0&
0+
#810000
b11111 0
1&
1+
#820000
0&
0+
#830000
b100000 0
1&
1+
#840000
0&
0+
#850000
b100001 0
1&
1+
#860000
0&
0+
#870000
b100010 0
1&
1+
#880000
0&
0+
#890000
b100011 0
1&
1+
#900000
0&
0+
#910000
b100100 0
1&
1+
#920000
0&
0+
#930000
b100101 0
1&
1+
#940000
0&
0+
#950000
b100110 0
1&
1+
#960000
0&
0+
#970000
b100111 0
1&
1+
#980000
0&
0+
#990000
b101000 0
1&
1+
#1000000
0&
0+
#1010000
b101001 0
1&
1+
#1020000
0&
0+
#1030000
b101010 0
1&
1+
#1040000
0&
0+
#1050000
b101011 0
1&
1+
#1060000
0&
0+
#1070000
b101100 0
1&
1+
#1080000
0&
0+
#1090000
b101101 0
1&
1+
#1100000
0&
0+
#1110000
b101110 0
1&
1+
#1120000
0&
0+
#1130000
b101111 0
1&
1+
#1140000
0&
0+
#1150000
b110000 0
1&
1+
#1160000
0&
0+
#1170000
b110001 0
1&
1+
#1180000
0&
0+
#1190000
b110010 0
1&
1+
#1200000
0&
0+
#1210000
b110011 0
1&
1+
#1220000
0&
0+
#1230000
b110100 0
1&
1+
#1240000
0&
0+
#1250000
b110101 0
1&
1+
#1260000
0&
0+
#1270000
b110110 0
1&
1+
#1280000
0&
0+
#1290000
b110111 0
1&
1+
#1300000
0&
0+
#1310000
b111000 0
1&
1+
#1320000
0&
0+
#1330000
b111001 0
1&
1+
#1340000
0&
0+
#1350000
b111010 0
1&
1+
#1360000
0&
0+
#1370000
b111011 0
1&
1+
#1380000
0&
0+
#1390000
b111100 0
1&
1+
#1400000
0&
0+
#1410000
b111101 0
1&
1+
#1420000
0&
0+
#1430000
b111110 0
1&
1+
#1440000
0&
0+
#1450000
b111111 0
1&
1+
#1460000
0&
0+
#1470000
b1000000 0
1&
1+
#1480000
0&
0+
#1490000
b1000001 0
1&
1+
#1500000
0&
0+
#1510000
b1000010 0
1&
1+
#1520000
0&
0+
#1530000
b1000011 0
1&
1+
#1540000
0&
0+
#1550000
b1000100 0
1&
1+
#1560000
0&
0+
#1570000
b1000101 0
1&
1+
#1580000
0&
0+
#1590000
b1000110 0
1&
1+
#1600000
0&
0+
#1610000
b1000111 0
1&
1+
#1620000
0&
0+
#1630000
b1001000 0
1&
1+
#1640000
0&
0+
#1650000
b1001001 0
1&
1+
#1660000
0&
0+
#1670000
b1001010 0
1&
1+
#1680000
0&
0+
#1690000
b1001011 0
1&
1+
#1700000
0&
0+
#1710000
b1001100 0
1&
1+
#1720000
0&
0+
#1730000
b1001101 0
1&
1+
#1740000
0&
0+
#1750000
b1001110 0
1&
1+
#1760000
0&
0+
#1770000
b1001111 0
1&
1+
#1780000
0&
0+
#1790000
b1010000 0
1&
1+
#1800000
0&
0+
#1810000
b1010001 0
1&
1+
#1820000
0&
0+
#1830000
b1010010 0
1&
1+
#1840000
0&
0+
#1850000
b1010011 0
1&
1+
#1860000
0&
0+
#1870000
b1010100 0
1&
1+
#1880000
0&
0+
#1890000
b1010101 0
1&
1+
#1900000
0&
0+
#1910000
b1010110 0
1&
1+
#1920000
0&
0+
#1930000
b1010111 0
1&
1+
#1940000
0&
0+
#1950000
b1011000 0
1&
1+
#1960000
0&
0+
#1970000
b1011001 0
1&
1+
#1980000
0&
0+
#1990000
b1011010 0
1&
1+
#2000000
0&
0+
#2010000
b1011011 0
1&
1+
#2020000
0&
0+
#2030000
b1011100 0
1&
1+
#2040000
0&
0+
#2050000
b1011101 0
1&
1+
#2060000
0&
0+
#2070000
b1011110 0
1&
1+
#2080000
0&
0+
#2090000
b1011111 0
1&
1+
#2100000
0&
0+
#2110000
b1100000 0
1&
1+
#2120000
0&
0+
#2130000
b1100001 0
1&
1+
#2140000
0&
0+
#2150000
b1100010 0
1&
1+
#2160000
0&
0+
#2170000
b1100011 0
1&
1+
#2180000
0&
0+
#2190000
b1100100 0
1&
1+
#2200000
0&
0+
#2210000
b1100101 0
1&
1+
#2220000
0&
0+
#2230000
b1100110 0
1&
1+
#2240000
0&
0+
#2250000
b1100111 0
1&
1+
#2260000
0&
0+
#2270000
b1101000 0
1&
1+
#2280000
0&
0+
#2290000
b1101001 0
1&
1+
#2300000
0&
0+
#2310000
b1101010 0
1&
1+
#2320000
0&
0+
#2330000
b1101011 0
1&
1+
#2340000
0&
0+
#2350000
b1101100 0
1&
1+
#2360000
0&
0+
#2370000
b1101101 0
1&
1+
#2380000
0&
0+
#2390000
b1101110 0
1&
1+
#2400000
0&
0+
#2410000
b1101111 0
1&
1+
#2420000
0&
0+
#2430000
b1110000 0
1&
1+
#2440000
0&
0+
#2450000
b1110001 0
1&
1+
#2460000
0&
0+
#2470000
b1110010 0
1&
1+
#2480000
0&
0+
#2490000
b1110011 0
1&
1+
#2500000
0&
0+
#2510000
b1110100 0
1&
1+
#2520000
0&
0+
#2530000
b1110101 0
1&
1+
#2540000
0&
0+
#2550000
b1110110 0
1&
1+
#2560000
0&
0+
#2570000
b1110111 0
1&
1+
#2580000
0&
0+
#2590000
b1111000 0
1&
1+
#2600000
0&
0+
#2610000
b1111001 0
1&
1+
#2620000
0&
0+
#2630000
b1111010 0
1&
1+
#2640000
0&
0+
#2650000
b1111011 0
1&
1+
#2660000
0&
0+
#2670000
b1111100 0
1&
1+
#2680000
0&
0+
#2690000
b1111101 0
1&
1+
#2700000
0&
0+
#2710000
b1111110 0
1&
1+
#2720000
0&
0+
#2730000
b1111111 0
1&
1+
#2740000
0&
0+
#2750000
b10000000 0
1&
1+
#2760000
0&
0+
#2770000
b10000001 0
1&
1+
#2780000
0&
0+
#2790000
b10000010 0
1&
1+
#2800000
0&
0+
#2810000
b10000011 0
1&
1+
#2820000
0&
0+
#2830000
b10000100 0
1&
1+
#2840000
0&
0+
#2850000
b10000101 0
1&
1+
#2860000
0&
0+
#2870000
b10000110 0
1&
1+
#2880000
0&
0+
#2890000
b10000111 0
1&
1+
#2900000
0&
0+
#2910000
b10001000 0
1&
1+
#2920000
0&
0+
#2930000
b10001001 0
1&
1+
#2940000
0&
0+
#2950000
b10001010 0
1&
1+
#2960000
0&
0+
#2970000
b10001011 0
1&
1+
#2980000
0&
0+
#2990000
b10001100 0
1&
1+
#3000000
0&
0+
#3010000
b10001101 0
1&
1+
#3020000
0&
0+
#3030000
b10001110 0
1&
1+
#3040000
0&
0+
#3050000
b10001111 0
1&
1+
#3060000
0&
0+
#3070000
b10010000 0
1&
1+
#3080000
0&
0+
#3090000
b10010001 0
1&
1+
#3100000
0&
0+
#3110000
b10010010 0
1&
1+
#3120000
0&
0+
#3130000
b10010011 0
1&
1+
#3140000
0&
0+
#3150000
b10010100 0
1&
1+
#3160000
0&
0+
#3170000
b10010101 0
1&
1+
#3180000
0&
0+
#3190000
b10010110 0
1&
1+
#3200000
0&
0+
#3210000
b10010111 0
1&
1+
#3220000
0&
0+
#3230000
b10011000 0
1&
1+
#3240000
0&
0+
#3250000
b10011001 0
1&
1+
#3260000
0&
0+
#3270000
b10011010 0
1&
1+
#3280000
0&
0+
#3290000
b10011011 0
1&
1+
#3300000
0&
0+
#3310000
b10011100 0
1&
1+
#3320000
0&
0+
#3330000
b10011101 0
1&
1+
#3340000
0&
0+
#3350000
b10011110 0
1&
1+
#3360000
0&
0+
#3370000
b10011111 0
1&
1+
#3380000
0&
0+
#3390000
b10100000 0
1&
1+
#3400000
0&
0+
#3410000
b10100001 0
1&
1+
#3420000
0&
0+
#3430000
b10100010 0
1&
1+
#3440000
0&
0+
#3450000
b10100011 0
1&
1+
#3460000
0&
0+
#3470000
b10100100 0
1&
1+
#3480000
0&
0+
#3490000
b10100101 0
1&
1+
#3500000
0&
0+
#3510000
b10100110 0
1&
1+
#3520000
0&
0+
#3530000
b10100111 0
1&
1+
#3540000
0&
0+
#3550000
b10101000 0
1&
1+
#3560000
0&
0+
#3570000
b10101001 0
1&
1+
#3580000
0&
0+
#3590000
b10101010 0
1&
1+
#3600000
0&
0+
#3610000
b10101011 0
1&
1+
#3620000
0&
0+
#3630000
b10101100 0
1&
1+
#3640000
0&
0+
#3650000
b10101101 0
1&
1+
#3660000
0&
0+
#3670000
b10101110 0
1&
1+
#3680000
0&
0+
#3690000
b10101111 0
1&
1+
#3700000
0&
0+
#3710000
b10110000 0
1&
1+
#3720000
0&
0+
#3730000
b10110001 0
1&
1+
#3740000
0&
0+
#3750000
b10110010 0
1&
1+
#3760000
0&
0+
#3770000
b10110011 0
1&
1+
#3780000
0&
0+
#3790000
b10110100 0
1&
1+
#3800000
0&
0+
#3810000
b10110101 0
1&
1+
#3820000
0&
0+
#3830000
b10110110 0
1&
1+
#3840000
0&
0+
#3850000
b10110111 0
1&
1+
#3860000
0&
0+
#3870000
b10111000 0
1&
1+
#3880000
0&
0+
#3890000
b10111001 0
1&
1+
#3900000
0&
0+
#3910000
b10111010 0
1&
1+
#3920000
0&
0+
#3930000
b10111011 0
1&
1+
#3940000
0&
0+
#3950000
b10111100 0
1&
1+
#3960000
0&
0+
#3970000
b10111101 0
1&
1+
#3980000
0&
0+
#3990000
b10111110 0
1&
1+
#4000000
0&
0+
#4010000
b10111111 0
1&
1+
#4020000
0&
0+
#4030000
b11000000 0
1&
1+
#4040000
0&
0+
#4050000
b11000001 0
1&
1+
#4060000
0&
0+
#4070000
b11000010 0
1&
1+
#4080000
0&
0+
#4090000
b11000011 0
1&
1+
#4100000
0&
0+
#4110000
b11000100 0
1&
1+
#4120000
0&
0+
#4130000
b11000101 0
1&
1+
#4140000
0&
0+
#4150000
b11000110 0
1&
1+
#4160000
0&
0+
#4170000
b11000111 0
1&
1+
#4180000
0&
0+
#4190000
b11001000 0
1&
1+
#4200000
0&
0+
#4210000
b11001001 0
1&
1+
#4220000
0&
0+
#4230000
b11001010 0
1&
1+
#4240000
0&
0+
#4250000
b11001011 0
1&
1+
#4260000
0&
0+
#4270000
b11001100 0
1&
1+
#4280000
0&
0+
#4290000
b11001101 0
1&
1+
#4300000
0&
0+
#4310000
b11001110 0
1&
1+
#4320000
0&
0+
#4330000
b11001111 0
1&
1+
#4340000
0&
0+
#4350000
b11010000 0
1&
1+
#4360000
0&
0+
#4370000
b11010001 0
1&
1+
#4380000
0&
0+
#4390000
b11010010 0
1&
1+
#4400000
0&
0+
#4410000
b11010011 0
1&
1+
#4420000
0&
0+
#4430000
b11010100 0
1&
1+
#4440000
0&
0+
#4450000
b11010101 0
1&
1+
#4460000
0&
0+
#4470000
b11010110 0
1&
1+
#4480000
0&
0+
#4490000
b11010111 0
1&
1+
#4500000
0&
0+
#4510000
b11011000 0
1&
1+
#4520000
0&
0+
#4530000
b11011001 0
1&
1+
#4540000
0&
0+
#4550000
b11011010 0
1&
1+
#4560000
0&
0+
#4570000
b11011011 0
1&
1+
#4580000
0&
0+
#4590000
b11011100 0
1&
1+
#4600000
0&
0+
#4610000
b11011101 0
1&
1+
#4620000
0&
0+
#4630000
b11011110 0
1&
1+
#4640000
0&
0+
#4650000
b11011111 0
1&
1+
#4660000
0&
0+
#4670000
b11100000 0
1&
1+
#4680000
0&
0+
#4690000
b11100001 0
1&
1+
#4700000
0&
0+
#4710000
b11100010 0
1&
1+
#4720000
0&
0+
#4730000
b11100011 0
1&
1+
#4740000
0&
0+
#4750000
b11100100 0
1&
1+
#4760000
0&
0+
#4770000
b11100101 0
1&
1+
#4780000
0&
0+
#4790000
b11100110 0
1&
1+
#4800000
0&
0+
#4810000
b11100111 0
1&
1+
#4820000
0&
0+
#4830000
b11101000 0
1&
1+
#4840000
0&
0+
#4850000
b11101001 0
1&
1+
#4860000
0&
0+
#4870000
b11101010 0
1&
1+
#4880000
0&
0+
#4890000
b11101011 0
1&
1+
#4900000
0&
0+
#4910000
b11101100 0
1&
1+
#4920000
0&
0+
#4930000
b11101101 0
1&
1+
#4940000
0&
0+
#4950000
b11101110 0
1&
1+
#4960000
0&
0+
#4970000
b11101111 0
1&
1+
#4980000
0&
0+
#4990000
b11110000 0
1&
1+
#5000000
0&
0+
#5010000
b11110001 0
1&
1+
#5020000
0&
0+
#5030000
b11110010 0
1&
1+
#5040000
0&
0+
#5050000
b11110011 0
1&
1+
#5060000
0&
0+
#5070000
b11110100 0
1&
1+
#5080000
0&
0+
#5090000
b11110101 0
1&
1+
#5100000
0&
0+
#5110000
b11110110 0
1&
1+
#5120000
0&
0+
#5130000
b11110111 0
1&
1+
#5140000
0&
0+
#5150000
b11111000 0
1&
1+
#5160000
0&
0+
#5170000
b11111001 0
1&
1+
#5180000
0&
0+
#5190000
b11111010 0
1&
1+
#5200000
0&
0+
#5210000
b11111011 0
1&
1+
#5220000
0&
0+
#5230000
b11111100 0
1&
1+
#5240000
0&
0+
#5250000
b11111101 0
1&
1+
#5260000
0&
0+
#5270000
b11111110 0
1&
1+
#5280000
0&
0+
#5290000
b11111111 0
1&
1+
#5300000
0&
0+
#5310000
b100000000 0
1&
1+
#5320000
0&
0+
#5330000
b100000001 0
1&
1+
#5340000
0&
0+
#5350000
b100000010 0
1&
1+
#5360000
0&
0+
#5370000
b100000011 0
1&
1+
#5380000
0&
0+
#5390000
b100000100 0
1&
1+
#5400000
0&
0+
#5410000
b100000101 0
1&
1+
#5420000
0&
0+
#5430000
b100000110 0
1&
1+
#5440000
0&
0+
#5450000
b100000111 0
1&
1+
#5460000
0&
0+
#5470000
b100001000 0
1&
1+
#5480000
0&
0+
#5490000
b100001001 0
1&
1+
#5500000
0&
0+
#5510000
b100001010 0
1&
1+
#5520000
0&
0+
#5530000
b100001011 0
1&
1+
#5540000
0&
0+
#5550000
b100001100 0
1&
1+
#5560000
0&
0+
#5570000
b100001101 0
1&
1+
#5580000
0&
0+
#5590000
b100001110 0
1&
1+
#5600000
0&
0+
#5610000
b100001111 0
1&
1+
#5620000
0&
0+
#5630000
b100010000 0
1&
1+
#5640000
0&
0+
#5650000
b100010001 0
1&
1+
#5660000
0&
0+
#5670000
b100010010 0
1&
1+
#5680000
0&
0+
#5690000
b100010011 0
1&
1+
#5700000
0&
0+
#5710000
b100010100 0
1&
1+
#5720000
0&
0+
#5730000
b100010101 0
1&
1+
#5740000
0&
0+
#5750000
b100010110 0
1&
1+
#5760000
0&
0+
#5770000
b100010111 0
1&
1+
#5780000
0&
0+
#5790000
b100011000 0
1&
1+
#5800000
0&
0+
#5810000
b100011001 0
1&
1+
#5820000
0&
0+
#5830000
b100011010 0
1&
1+
#5840000
0&
0+
#5850000
b100011011 0
1&
1+
#5860000
0&
0+
#5870000
b100011100 0
1&
1+
#5880000
0&
0+
#5890000
b100011101 0
1&
1+
#5900000
0&
0+
#5910000
b100011110 0
1&
1+
#5920000
0&
0+
#5930000
b100011111 0
1&
1+
#5940000
0&
0+
#5950000
b100100000 0
1&
1+
#5960000
0&
0+
#5970000
b100100001 0
1&
1+
#5980000
0&
0+
#5990000
b100100010 0
1&
1+
#6000000
0&
0+
#6010000
b100100011 0
1&
1+
#6020000
0&
0+
#6030000
b100100100 0
1&
1+
#6040000
0&
0+
#6050000
b100100101 0
1&
1+
#6060000
0&
0+
#6070000
b100100110 0
1&
1+
#6080000
0&
0+
#6090000
b100100111 0
1&
1+
#6100000
0&
0+
#6110000
b100101000 0
1&
1+
#6120000
0&
0+
#6130000
b100101001 0
1&
1+
#6140000
0&
0+
#6150000
b100101010 0
1&
1+
#6160000
0&
0+
#6170000
b100101011 0
1&
1+
#6180000
0&
0+
#6190000
b100101100 0
1&
1+
#6200000
0&
0+
#6210000
b100101101 0
1&
1+
#6220000
0&
0+
#6230000
b100101110 0
1&
1+
#6240000
0&
0+
#6250000
b100101111 0
1&
1+
#6260000
0&
0+
#6270000
b100110000 0
1&
1+
#6280000
0&
0+
#6290000
b100110001 0
1&
1+
#6300000
0&
0+
#6310000
b100110010 0
1&
1+
#6320000
0&
0+
#6330000
b100110011 0
1&
1+
#6340000
0&
0+
#6350000
b100110100 0
1&
1+
#6360000
0&
0+
#6370000
b100110101 0
1&
1+
#6380000
0&
0+
#6390000
b100110110 0
1&
1+
#6400000
0&
0+
#6410000
b100110111 0
1&
1+
#6420000
0&
0+
#6430000
b100111000 0
1&
1+
#6440000
0&
0+
#6450000
b100111001 0
1&
1+
#6460000
0&
0+
#6470000
b100111010 0
1&
1+
#6480000
0&
0+
#6490000
b100111011 0
1&
1+
#6500000
0&
0+
#6510000
b100111100 0
1&
1+
#6520000
0&
0+
#6530000
b100111101 0
1&
1+
#6540000
0&
0+
#6550000
b100111110 0
1&
1+
#6560000
0&
0+
#6570000
b100111111 0
1&
1+
#6580000
0&
0+
#6590000
b101000000 0
1&
1+
#6600000
0&
0+
#6610000
b101000001 0
1&
1+
#6620000
0&
0+
#6630000
b101000010 0
1&
1+
#6640000
0&
0+
#6650000
b101000011 0
1&
1+
#6660000
0&
0+
